{
  "brand": {
    "name": "Dodge",
    "slug": "dodge",
    "tone": "premium"
  },
  "model": {
    "name": "Dodge Durango",
    "slug": "durango",
    "legacySlug": "dodge-durango"
  },
  "seo": {
    "title": "Dodge Durango Engine Replacement - Compare Prices UK",
    "description": "Dodge Durango engine replacement cost guide. Compare rebuilt, reconditioned & used engine prices from £3,500. 12-month warranty & UK supply fit specialists.",
    "canonical": "/dodge/durango"
  },
  "assets": {
    "mainImage": "/images/brands/dodge/models/dodge-durango-model-card.png",
    "smallImage": "/images/brands/dodge/models/dodge-durango-model-card.png",
    "heroBg": "/images/brands/dodge/models/dodge-durango-model-card.png",
    "howItWorksBg": "/images/brands/dodge/brand/dodge-how-it-works-bg.webp",
    "engineCodesBg": "/images/brands/dodge/brand/dodge-engine-codes-bg.webp",
    "engineTypesBg": "/images/brands/dodge/brand/dodge-engine-types-bg.webp",
    "engineSizesBg": "/images/brands/dodge/brand/dodge-engine-sizes-bg.webp",
    "fuelTypesBg": "/images/brands/dodge/brand/dodge-fuel-types-bg.webp",
    "ctaImage": "/images/brands/dodge/models/dodge-durango-model-card.png"
  },
  "sections": {
    "hero": {
      "tag": "Dodge ENGINE MARKETPLACE",
      "h1": "Dodge Durango Engine Replacement - Compare Prices & Save",
      "subheading": "Get quotes today from trusted UK Dodge Durango engine specialists. Compare prices on reconditioned, rebuilt and used engines - supply & fit available.",
      "trustBadges": [
        "Supply & Fit Available",
        "12-Month Warranty",
        "Nationwide Delivery",
        "100+ Suppliers"
      ],
      "ctaLinkText": "Get Free Dodge Durango Engine Quotes →",
      "supportingText": "Get tailored Dodge Durango engine quotes from vetted UK specialists.",
      "ticker": "● Instant Quotes · No Obligation · 100% Free · Reconditioned · Rebuilt · Used · Supply & Fit Available · UK-Wide Network",
      "form": {
        "heading": "Find Your Dodge Durango Engine",
        "subtitle": "Enter your registration number to compare Dodge Durango engine options.",
        "inputPlaceholder": "Enter Reg (e.g. AB12 CDE)",
        "buttonText": "Get Free Dodge Durango Engine Quotes →",
        "note": "🔒 Secure enquiry - no spam, no pressure. Genuine quotes only from vetted UK Dodge Durango specialists."
      },
      "imageAlt": "Dodge Durango engine replacement UK - compare reconditioned and rebuilt engine prices",
      "highlights": [
        {
          "title": "Dodge Durango 3.6L Pentastar Engines",
          "price": "from £3,500 to £5,500",
          "line1": "Dodge Durango 3.6L Pentastar Engines - from £3,500 to £5,500",
          "line2": "-> Rebuilt units from £3,500 · Common codes: ERB, ESG, ESH, ESA",
          "detail": "-> Rebuilt units from £3,500 · Common codes: ERB, ESG, ESH, ESA",
          "image": "",
          "imageAlt": "Dodge Durango Pentastar 3.6L V6 engine - ERB ESG ESH rebuilt reconditioned UK"
        },
        {
          "title": "Dodge Durango 5.7L HEMI Engines",
          "price": "from £4,200 to £5,800",
          "line1": "Dodge Durango 5.7L HEMI Engines - from £4,200 to £5,800",
          "line2": "-> Rebuilt units from £4,200 · Common codes: EZH, EZH-T, EGG, 9EZH",
          "detail": "-> Rebuilt units from £4,200 · Common codes: EZH, EZH-T, EGG, 9EZH",
          "image": "",
          "imageAlt": "Dodge Durango HEMI 5.7L V8 engine - EZH EZH-T EGG rebuilt reconditioned UK"
        },
        {
          "title": "Dodge Durango 3.0L EcoDiesel Engines",
          "price": "from £4,800 to £6,500",
          "line1": "Dodge Durango 3.0L EcoDiesel Engines - from £4,800 to £6,500",
          "line2": "-> Rebuilt units from £4,800 · Common codes: EXF",
          "detail": "-> Rebuilt units from £4,800 · Common codes: EXF",
          "image": "",
          "imageAlt": "Dodge Durango EcoDiesel 3.0L V6 engine - EXF rebuilt reconditioned UK specialist"
        }
      ],
      "headingLines": [
        "Dodge Durango Engine Replacement",
        "Compare Prices & Save"
      ],
      "mobileBar": {
        "brandText": "ENGINEMARKET",
        "callLabel": "Call",
        "quoteLabel": "GET QUOTES"
      },
      "registrationInput": {
        "label": "Enter your vehicle registration",
        "platePlaceholder": "AB12 CDE",
        "countryCode": "UK",
        "countryLabel": "United Kingdom"
      }
    },
    "howItWorks": {
      "tag": "How It Works",
      "h2": "3 Simple Steps to Finding the Best Dodge Durango Replacement Engine",
      "cards": [
        {
          "number": 1,
          "icon": "registration",
          "front": {
            "h3": "Enter Your Dodge Durango Registration",
            "text": "Instantly verify your exact model, engine code and fuel type via DVLA - SXT to SRT Hellcat."
          },
          "back": {
            "heading": "Your Car, Precisely Identified",
            "text": "Engines Market uses the official DVLA database to pull accurate details about your Durango, not just model name.",
            "bullets": [
              "Your Precise Model - from SXT, GT, Citadel, R/T to SRT 392, SRT Hellcat",
              "Your Engine Code - ERB, EZH, EXF, ESG and more",
              "Vehicle Specs Check - fuel type, engine size, year, variant - all verified instantly",
              "No paperwork, no guesswork, 100% free."
            ]
          }
        },
        {
          "number": 2,
          "icon": "quote",
          "front": {
            "h3": "Get Quotes from Dodge Engine Specialists",
            "text": "Same-day quotes from vetted UK suppliers — full breakdown, no obligation."
          },
          "back": {
            "heading": "Quotes You Can Trust",
            "text": "Your verified details are securely shared with up to 10 of our most relevant UK suppliers, matched to your variant and location.",
            "bullets": [
              "Vetted UK Suppliers — specialists who understand Dodge petrol and diesel engines",
              "Same-Day Quotes — usually within hours, not days",
              "Supply & Fit Service — or supply-only to your own garage",
              "Full Breakdown — price, warranty length, delivery estimate and fitting cost all shown clearly",
              "No hidden fees. No sales calls unless you approve."
            ]
          }
        },
        {
          "number": 3,
          "icon": "shield",
          "front": {
            "h3": "Choose the Best Deal & Save",
            "text": "Compare supplier reviews, warranty and price — then pick the right one for you."
          },
          "back": {
            "heading": "Your Choice, Your Control",
            "text": "You decide which specialist to go with. We simply make the search fast, safe and transparent.",
            "bullets": [
              "Online Reviews — read real customer feedback",
              "Warranty Length — minimum 12 months, often 24 months on rebuilt units",
              "Terms of Service — including collection, fitting and aftercare",
              "Technical Expertise — see each supplier's Dodge experience",
              "You deal directly with your chosen provider. No pressure, no commitment until you're ready."
            ]
          }
        }
      ],
      "tagline": "Get Instant Quotes from Dodge Engine Specialists Across the UK — 100% free, no obligation. Most replacements completed within 5–7 days.",
      "headingLines": [
        "3 Simple Steps",
        "to Finding the Best Dodge Durango Replacement Engine"
      ],
      "ui": {
        "stepLabel": "Step",
        "desktopClosedLabel": "Click to expand",
        "desktopOpenLabel": "Click to view details",
        "mobileOpenLabel": "Tap to flip",
        "mobileCloseLabel": "Tap to flip back",
        "footerNote": "Most replacements completed within 3-5 days.",
        "mobileTrustItems": [
          "12-Month Warranty",
          "Supply & Fit Available",
          "Nationwide Delivery",
          "Trusted UK Suppliers"
        ]
      }
    },
    "engineIntelligence": {
      "tag": "Engine Intelligence",
      "h2": "Dodge Durango Engines - Codes, Common Failures & Replacement Costs",
      "description": "The cards below cover the main engines fitted to the Dodge Durango in the UK, including documented failure causes, variant production years, and typical rebuilt engine costs based on current UK market data.",
      "cards": [
        {
          "code": "ERB",
          "imagePlaceholder": "",
          "altText": "Dodge Durango ERB engine - petrol 3.6L replacement UK",
          "productionHistory": [
            "SXT, GT, Citadel - 2011-2024",
            "AWD and RWD variants - 2011-2024",
            "Pre-facelift WK2 and facelift WD chassis - 2011-2024"
          ],
          "knownFailures": [
            "Timing chain stretch - tensioner wear causes rattling noise from 60k-100k miles.",
            "Water pump failure - internal leak leads to coolant loss and overheating risk.",
            "Cam phaser rattle - VVT actuator wear on cold start, common after 80k miles."
          ],
          "specs": "Petrol · 3.6L · 293-295hp · Naturally Aspirated",
          "replacementCost": "Typical UK rebuilt engine: £3,500-£5,500 (supply only)"
        },
        {
          "code": "EZH",
          "imagePlaceholder": "",
          "altText": "Dodge Durango EZH engine - petrol 5.7L replacement UK",
          "productionHistory": [
            "R/T, Citadel, GT Plus - 2011-2024",
            "AWD and RWD variants - 2011-2024",
            "MDS cylinder deactivation equipped models - 2011-2024"
          ],
          "knownFailures": [
            "Lifter tick - collapsed hydraulic lifters cause ticking noise, often 70k+ miles.",
            "Valve seat recession - intake valve seat dropout causes compression loss and misfire.",
            "MDS solenoid failure - cylinder deactivation faults trigger rough idle and warning lights."
          ],
          "specs": "Petrol · 5.7L · 360-395hp · Naturally Aspirated",
          "replacementCost": "Typical UK rebuilt engine: £4,200-£5,800 (supply only)"
        },
        {
          "code": "EXF",
          "imagePlaceholder": "",
          "altText": "Dodge Durango EXF engine - diesel 3.0L replacement UK",
          "productionHistory": [
            "EcoDiesel variants - 2014-2020 (limited UK availability)",
            "AWD only configuration - 2014-2020",
            "WK2 chassis pre-facelift models - 2014-2020"
          ],
          "knownFailures": [
            "EGR cooler crack - thermal fatigue causes coolant leak into intake, risk of combustion.",
            "Injector carbon buildup - diesel injector coking leads to misfire and rough running.",
            "DPF regeneration issues - blocked filter from short-journey driving causes power loss."
          ],
          "specs": "Diesel · 3.0L · 240-260hp · Turbocharged",
          "replacementCost": "Typical UK rebuilt engine: £4,800-£6,500 (supply only) Estimated from comparable EXF units - actual quotes may vary."
        }
      ],
      "headingLines": [
        "Dodge Durango Engines",
        "Codes, Common Failures & Replacement Costs"
      ],
      "imageAlt": "Dodge Durango engine intelligence reference",
      "ui": {
        "productionHistoryLabel": "Production History",
        "knownFailuresLabel": "Known Failures",
        "specsLabel": "Specs",
        "replacementCostLabel": "Replacement Cost"
      }
    },
    "liveMarketPrices": {
      "tag": "Live UK Engine Market Data",
      "h2": "",
      "h3": "",
      "introBullets": [
        {
          "label": "Live market context",
          "text": "See realistic rebuilt-engine quote ranges across documented Dodge Durango variants."
        },
        {
          "label": "Variant specific",
          "text": "Each row highlights the exact variant, failure trigger, engine code and fuel type behind replacement demand."
        },
        {
          "label": "Specialist pricing",
          "text": "These figures reflect the independent UK engine supplier and rebuilder market rather than main dealer replacement costs."
        },
        {
          "label": "Quote benchmark",
          "text": "Use the feed to benchmark your own enquiry before comparing live quotes for your registration."
        }
      ],
      "cta": {
        "heading": "Benchmark your own Dodge Durango quote",
        "text": "Use these recent enquiry ranges to understand the market, then compare tailored quotes for your exact Dodge Durango engine code.",
        "buttonText": "Compare My Dodge Durango Engine",
        "note": "Prices vary by engine code, variant, damage severity, mileage, supplier stock and whether you need supply-only or supply and fit."
      },
      "badges": [
        "0 recent enquiries visible",
        "Typical rebuilt market ranges",
        "Engine-code matched rows",
        "UK specialist network"
      ],
      "feed": {
        "isDynamic": false,
        "rowsCount": 0,
        "columns": [
          "Year",
          "Model",
          "Engine Code",
          "Fuel",
          "Avg. Quoted Price",
          "Reported Issue"
        ],
        "timestampLabel": "Last Updated",
        "refreshLabel": "Refresh feed",
        "density": "premium",
        "visibleRows": 0,
        "entries": []
      },
      "headingLines": [],
      "imageAlt": "Dodge Durango live market price reference",
      "filterTabs": [
        {
          "key": "all",
          "label": "All",
          "matchers": []
        },
        {
          "key": "dodge-durango-sxt-engine",
          "label": "Dodge Durango SXT",
          "matchers": [
            "dodge durango sxt",
            "dodge durango sxt engine"
          ]
        },
        {
          "key": "dodge-durango-gt-engine",
          "label": "Dodge Durango GT",
          "matchers": [
            "dodge durango gt",
            "dodge durango gt engine"
          ]
        },
        {
          "key": "dodge-durango-citadel-engine",
          "label": "Dodge Durango Citadel",
          "matchers": [
            "dodge durango citadel",
            "dodge durango citadel engine"
          ]
        },
        {
          "key": "dodge-durango-r-t-engine",
          "label": "Dodge Durango R/T",
          "matchers": [
            "dodge durango r/t",
            "dodge durango r t engine"
          ]
        },
        {
          "key": "dodge-durango-srt-392-engine",
          "label": "Dodge Durango SRT 392",
          "matchers": [
            "dodge durango srt 392",
            "dodge durango srt 392 engine"
          ]
        },
        {
          "key": "dodge-durango-srt-hellcat-engine",
          "label": "Dodge Durango SRT Hellcat",
          "matchers": [
            "dodge durango srt hellcat",
            "dodge durango srt hellcat engine"
          ]
        },
        {
          "key": "dodge-durango-ecodiesel-engine",
          "label": "Dodge Durango EcoDiesel",
          "matchers": [
            "dodge durango ecodiesel",
            "dodge durango ecodiesel engine"
          ]
        },
        {
          "key": "dodge-durango-awd-engine",
          "label": "Dodge Durango AWD",
          "matchers": [
            "dodge durango awd",
            "dodge durango awd engine"
          ]
        },
        {
          "key": "dodge-durango-rwd-engine",
          "label": "Dodge Durango RWD",
          "matchers": [
            "dodge durango rwd",
            "dodge durango rwd engine"
          ]
        },
        {
          "key": "dodge-durango-grey-import-engine",
          "label": "Dodge Durango Grey Import",
          "matchers": [
            "dodge durango grey import",
            "dodge durango grey import engine"
          ]
        },
        {
          "key": "dodge-durango-wk2-pre-facelift-engine",
          "label": "Dodge Durango WK2 Pre-Facelift",
          "matchers": [
            "dodge durango wk2 pre-facelift",
            "dodge durango wk2 pre facelift engine"
          ]
        },
        {
          "key": "dodge-durango-wd-facelift-engine",
          "label": "Dodge Durango WD Facelift",
          "matchers": [
            "dodge durango wd facelift",
            "dodge durango wd facelift engine"
          ]
        }
      ],
      "ui": {
        "showingSingleLabel": "entry",
        "showingPluralLabel": "entries",
        "acrossAllLabel": "across all models",
        "noEntriesLabel": "No entries match that model filter yet.",
        "updatedLabel": "Last updated:",
        "ctaLabel": "Live Quote Benchmark"
      }
    },
    "reviews": {
      "tag": "Customer Reviews",
      "h2": "Trusted by Dodge Durango Owners Across the UK",
      "rating": {
        "value": 4.8,
        "count": 1000,
        "summary": "Rated 4.8 out of 5 by verified customers who sourced reconditioned and used Dodge engines through EngineMarket.",
        "basedOn": "Based on real post-sale feedback from buyers matched with our network of UK engine specialists."
      },
      "reviews": [
        {
          "text": "Thanks to EngineMarket, I saved over £1,000 on my Dodge engine and found a solid local specialist quickly.",
          "name": "Jimmy",
          "location": "London"
        },
        {
          "text": "Got multiple quotes for my Dodge within hours and the whole process felt straightforward.",
          "name": "Pete",
          "location": "Leeds"
        },
        {
          "text": "I wasn't sure which Dodge engine I needed, but the quote process helped me narrow it down fast.",
          "name": "Sophie",
          "location": "Birmingham"
        },
        {
          "text": "Fast turnaround, clear pricing, and the warranty gave me real peace of mind for my Dodge.",
          "name": "Ahmed",
          "location": "Bradford"
        },
        {
          "text": "One of the easiest car-related experiences I've had. Honest, quick, and much cheaper than expected.",
          "name": "Liam",
          "location": "Manchester"
        },
        {
          "text": "EngineMarket made a stressful Dodge engine failure much easier to deal with from start to finish.",
          "name": "Tom",
          "location": "Glasgow"
        }
      ],
      "leaveReviewCta": {
        "text": "Had a great experience?",
        "linkText": "Leave a review ->"
      }
    },
    "variantCoverage": {
      "tag": "Models We Cover",
      "h2": "Dodge Durango Engine Replacement - All Variants Covered",
      "subheading": "From the economical SXT to the high‑performance SRT Hellcat, compare rebuilt, reconditioned and used engine prices from our network of UK Dodge Durango engine specialists - typical price range for a rebuilt unit with 12‑month warranty, supply & fit available nationwide.",
      "groups": [
        {
          "title": "Core Petrol Range",
          "cardSlugs": [
            "dodge-durango-sxt-engine",
            "dodge-durango-gt-engine",
            "dodge-durango-citadel-engine",
            "dodge-durango-r-t-engine"
          ]
        },
        {
          "title": "Performance & Specialist Range",
          "cardSlugs": [
            "dodge-durango-srt-392-engine",
            "dodge-durango-srt-hellcat-engine",
            "dodge-durango-ecodiesel-engine"
          ]
        },
        {
          "title": "Drivetrain & Import Specific",
          "cardSlugs": [
            "dodge-durango-awd-engine",
            "dodge-durango-rwd-engine",
            "dodge-durango-grey-import-engine",
            "dodge-durango-wk2-pre-facelift-engine",
            "dodge-durango-wd-facelift-engine"
          ]
        }
      ],
      "cards": [
        {
          "h3": "Dodge Durango SXT Engine Replacement",
          "slug": "dodge-durango-sxt-engine",
          "subtitle": "ERB 3.6L Petrol Â· 293hp Â· 2011-2024",
          "priceRange": "£3,500-£5,500",
          "cta": "Compare SXT Engine Prices",
          "engineCodes": [
            "ERB"
          ],
          "fuel": "Petrol",
          "power": "293hp",
          "years": "2011-2024",
          "image": ""
        },
        {
          "h3": "Dodge Durango GT Engine Replacement",
          "slug": "dodge-durango-gt-engine",
          "subtitle": "ERB/EZH 3.6L/5.7L Petrol Â· 293-360hp Â· 2011-2024",
          "priceRange": "£3,500-£5,800",
          "cta": "Compare GT Engine Prices",
          "engineCodes": [
            "ERB",
            "EZH"
          ],
          "fuel": "Petrol",
          "power": "293-360hp",
          "years": "2011-2024",
          "image": ""
        },
        {
          "h3": "Dodge Durango Citadel Engine Replacement",
          "slug": "dodge-durango-citadel-engine",
          "subtitle": "EZH 5.7L Petrol Â· 360hp Â· 2011-2024",
          "priceRange": "£4,200-£5,800",
          "cta": "Compare Citadel Engine Prices",
          "engineCodes": [
            "EZH"
          ],
          "fuel": "Petrol",
          "power": "360hp",
          "years": "2011-2024",
          "image": ""
        },
        {
          "h3": "Dodge Durango R/T Engine Replacement",
          "slug": "dodge-durango-r-t-engine",
          "subtitle": "EZH 5.7L HEMI Petrol Â· 360hp Â· 2011-2024",
          "priceRange": "£4,200-£5,800",
          "cta": "Compare R/T Engine Prices",
          "engineCodes": [
            "EZH"
          ],
          "fuel": "Petrol",
          "power": "360hp",
          "years": "2011-2024",
          "image": ""
        },
        {
          "h3": "Dodge Durango SRT 392 Engine Replacement",
          "slug": "dodge-durango-srt-392-engine",
          "subtitle": "ESG 6.4L HEMI Petrol Â· 475hp Â· 2018-2024",
          "priceRange": "£6,500-£9,500",
          "cta": "Compare SRT 392 Engine Prices",
          "engineCodes": [
            "ESG"
          ],
          "fuel": "Petrol",
          "power": "475hp",
          "years": "2018-2024",
          "image": ""
        },
        {
          "h3": "Dodge Durango SRT Hellcat Engine Replacement",
          "slug": "dodge-durango-srt-hellcat-engine",
          "subtitle": "EJH 6.2L Supercharged Petrol · 710hp · 2021-2024 · Rebuilt: £8,500-£12,500",
          "priceRange": "£8,500-£12,500",
          "cta": "Compare SRT Hellcat Engine Prices",
          "engineCodes": [
            "EJH"
          ],
          "fuel": "Petrol",
          "power": "710hp",
          "years": "2021-2024",
          "image": ""
        },
        {
          "h3": "Dodge Durango EcoDiesel Engine Replacement",
          "slug": "dodge-durango-ecodiesel-engine",
          "subtitle": "EXF 3.0L Diesel Â· 240hp Â· 2014-2020",
          "priceRange": "£4,800-£6,500",
          "cta": "Compare EcoDiesel Engine Prices",
          "engineCodes": [
            "EXF"
          ],
          "fuel": "Diesel",
          "power": "240hp",
          "years": "2014-2020",
          "image": ""
        },
        {
          "h3": "Dodge Durango AWD Engine Replacement",
          "slug": "dodge-durango-awd-engine",
          "subtitle": "ERB/EZH 3.6L/5.7L Petrol Â· 293-360hp Â· 2011-2024",
          "priceRange": "£3,500-£5,800",
          "cta": "Compare AWD Engine Prices",
          "engineCodes": [
            "ERB",
            "EZH"
          ],
          "fuel": "Petrol",
          "power": "293-360hp",
          "years": "2011-2024",
          "image": ""
        },
        {
          "h3": "Dodge Durango RWD Engine Replacement",
          "slug": "dodge-durango-rwd-engine",
          "subtitle": "ERB/EZH 3.6L/5.7L Petrol Â· 293-360hp Â· 2011-2024",
          "priceRange": "£3,500-£5,800",
          "cta": "Compare RWD Engine Prices",
          "engineCodes": [
            "ERB",
            "EZH"
          ],
          "fuel": "Petrol",
          "power": "293-360hp",
          "years": "2011-2024",
          "image": ""
        },
        {
          "h3": "Dodge Durango Grey Import Engine Replacement",
          "slug": "dodge-durango-grey-import-engine",
          "subtitle": "ERB/EZH/EXF 3.6L/5.7L/3.0L Â· 240-710hp Â· 2011-2024",
          "priceRange": "£3,500-£12,500",
          "cta": "Compare Grey Import Engine Prices",
          "engineCodes": [
            "ERB",
            "EZH",
            "EXF",
            "5.7L",
            "3.0L"
          ],
          "fuel": "",
          "power": "240-710hp",
          "years": "2011-2024",
          "image": ""
        },
        {
          "h3": "Dodge Durango WK2 Pre-Facelift Engine Replacement",
          "slug": "dodge-durango-wk2-pre-facelift-engine",
          "subtitle": "ERB/EZH 3.6L/5.7L Petrol Â· 293-360hp Â· 2011-2020",
          "priceRange": "£3,500-£5,800",
          "cta": "Compare WK2 Engine Prices",
          "engineCodes": [
            "ERB",
            "EZH"
          ],
          "fuel": "Petrol",
          "power": "293-360hp",
          "years": "2011-2020",
          "image": ""
        },
        {
          "h3": "Dodge Durango WD Facelift Engine Replacement",
          "slug": "dodge-durango-wd-facelift-engine",
          "subtitle": "ERB/EZH/ESG 3.6L/5.7L/6.4L Petrol Â· 293-475hp Â· 2021-2024",
          "priceRange": "£3,500-£9,500",
          "cta": "Compare WD Facelift Engine Prices",
          "engineCodes": [
            "ERB",
            "EZH",
            "ESG"
          ],
          "fuel": "Petrol",
          "power": "293-475hp",
          "years": "2021-2024",
          "image": ""
        }
      ],
      "directory": {
        "h3": "All Dodge Durango Variants - Engine Replacement Coverage",
        "intro": "A full alphabetical listing of every Dodge Durango trim covered by our network. All entries link to a dedicated variant page, where prices are further broken down by engine code, model year, and condition type. Click a live link to compare quotes.",
        "groups": [
          {
            "title": "Petrol Variants",
            "items": [
              "Citadel",
              "GT",
              "GT Plus",
              "GT Premium",
              "R/T",
              "R/T Plus",
              "R/T Premium",
              "SRT 392",
              "SRT 392 Plus",
              "SRT 392 Premium",
              "SRT Hellcat",
              "SRT Hellcat Hammerhead",
              "SRT Hellcat Silver Bullet",
              "SRT Hellcat Brass Monkey",
              "SXT",
              "SXT Plus"
            ]
          },
          {
            "title": "Diesel Variants",
            "items": [
              "EcoDiesel AWD",
              "EcoDiesel GT",
              "EcoDiesel Citadel"
            ]
          },
          {
            "title": "Performance Variants",
            "items": [
              "SRT 392",
              "SRT Hellcat",
              "SRT Hellcat Hammerhead",
              "SRT Hellcat Silver Bullet",
              "SRT Hellcat Brass Monkey"
            ]
          }
        ],
        "label": "Variant Directory"
      },
      "closing": "Not sure which variant your Dodge Durango is? Enter your registration number above - we'll identify the exact sub‑model, engine code and compatible replacement options instantly.",
      "engineGuide": {
        "tag": "Engine Codes",
        "h2": "Dodge Durango Engine Codes - Full Technical Specifications & Replacement Guide",
        "h3": "Every engine code fitted to the Dodge Durango across all generations, with technical specs, compatible variants and trims, known failure points, and average rebuilt prices from UK specialists. Select any engine code to compare quotes.",
        "families": [
          {
            "name": "Petrol Engines",
            "entries": [
              {
                "code": "ERB",
                "title": "3.6L Petrol",
                "familyHeading": "Pentastar V6 Family (2011-2024)",
                "history": "The most common UK Durango engine, introduced 2011 with aluminium block and VVT for efficiency.",
                "fuel": "Petrol",
                "size": "3.6 Litre",
                "power": "293-295 hp",
                "years": "2011-2024",
                "compatibleVariants": [
                  "SXT, GT, Citadel, AWD, RWD, WK2, WD"
                ],
                "commonFailures": [
                  "Timing chain stretch with tensioner wear - documented from 60k-100k miles on UK forums",
                  "Water pump internal seal failure - coolant loss without external leak, common after 80k miles",
                  "Cam phaser/VVT actuator rattle on cold start - wear item requiring replacement"
                ],
                "avgRebuiltPrice": "£3,500 - £5,500",
                "cta": "Get quotes for ERB Dodge Durango engine replacement",
                "image": "/images/brands/land-rover/engines/land-rover-508pn-engine.webp"
              },
              {
                "code": "ESG",
                "title": "3.6L Petrol",
                "familyHeading": "Pentastar V6 Family (2011-2024)",
                "history": "Updated Pentastar code for facelift WD chassis with refined calibration and emissions compliance.",
                "fuel": "Petrol",
                "size": "3.6 Litre",
                "power": "293-295 hp",
                "years": "2021-2024",
                "compatibleVariants": [
                  "SXT WD, GT WD, Citadel WD, AWD WD"
                ],
                "commonFailures": [
                  "Timing chain system wear - same root cause as ERB, preventative replacement recommended",
                  "Water pump failure - internal leak pattern consistent across Pentastar family",
                  "Oil consumption on higher mileage units - monitor levels between services"
                ],
                "avgRebuiltPrice": "£3,500 - £5,500",
                "cta": "Get quotes for ESG Dodge Durango engine replacement",
                "image": "/images/brands/land-rover/engines/land-rover-508pn-engine.webp"
              },
              {
                "code": "ESH",
                "title": "3.6L Petrol",
                "familyHeading": "Pentastar V6 Family (2011-2024)",
                "history": "Late-production Pentastar variant with updated PCM mapping for improved drivability.",
                "fuel": "Petrol",
                "size": "3.6 Litre",
                "power": "293-295 hp",
                "years": "2018-2024",
                "compatibleVariants": [
                  "GT, Citadel, R/T (where 3.6L specified), AWD"
                ],
                "commonFailures": [
                  "Timing chain tensioner wear - documented on UK owner forums for pre-2020 units",
                  "Water pump internal leak - same failure pattern as other Pentastar codes",
                  "VVT solenoid clogging - oil quality dependent, causes rough idle if neglected"
                ],
                "avgRebuiltPrice": "£3,500 - £5,500",
                "cta": "Get quotes for ESH Dodge Durango engine replacement",
                "image": "/images/brands/land-rover/engines/land-rover-508pn-engine.webp"
              },
              {
                "code": "EZH",
                "title": "5.7L Petrol",
                "familyHeading": "HEMI V8 Family (2011-2024)",
                "history": "The flagship HEMI for UK Durango, featuring MDS cylinder deactivation for fuel economy.",
                "fuel": "Petrol",
                "size": "5.7 Litre",
                "power": "360-395 hp",
                "years": "2011-2024",
                "compatibleVariants": [
                  "R/T, Citadel, GT Plus, AWD, RWD, WK2, WD"
                ],
                "commonFailures": [
                  "Hydraulic lifter collapse - \"lifter tick\" common from 70k miles, requires full valvetrain inspection",
                  "Valve seat recession - intake seat dropout causes compression loss, documented on high-mileage units",
                  "MDS solenoid failure - cylinder deactivation faults trigger warning lights and rough running"
                ],
                "avgRebuiltPrice": "£4,200 - £5,800",
                "cta": "Get quotes for EZH Dodge Durango engine replacement",
                "image": "/images/brands/land-rover/engines/land-rover-508pn-engine.webp"
              },
              {
                "code": "EZH-T",
                "title": "5.7L Petrol",
                "familyHeading": "HEMI V8 Family (2011-2024)",
                "history": "Updated HEMI code with revised MDS calibration for improved reliability and emissions.",
                "fuel": "Petrol",
                "size": "5.7 Litre",
                "power": "360-395 hp",
                "years": "2018-2024",
                "compatibleVariants": [
                  "R/T WD, Citadel WD, GT Plus WD, AWD WD"
                ],
                "commonFailures": [
                  "Lifter tick - same root cause as EZH, preventative inspection recommended at 60k miles",
                  "MDS solenoid wear - updated parts available, but failure pattern remains similar",
                  "Exhaust manifold bolt breakage - heat cycling causes leaks, common on pre-2020 units"
                ],
                "avgRebuiltPrice": "£4,200 - £5,800",
                "cta": "Get quotes for EZH-T Dodge Durango engine replacement",
                "image": "/images/brands/land-rover/engines/land-rover-508pn-engine.webp"
              },
              {
                "code": "EGG",
                "title": "5.7L Petrol",
                "familyHeading": "HEMI V8 Family (2011-2024)",
                "history": "Early HEMI code for pre-facelift WK2 Durango, foundational MDS implementation.",
                "fuel": "Petrol",
                "size": "5.7 Litre",
                "power": "360 hp",
                "years": "2011-2017",
                "compatibleVariants": [
                  "R/T WK2, Citadel WK2, AWD WK2"
                ],
                "commonFailures": [
                  "Lifter collapse - well-documented on UK forums for 2011-2015 units",
                  "Valve seat recession - higher incidence on early production engines",
                  "Timing chain guide wear - plastic guides can degrade, causing noise and potential failure"
                ],
                "avgRebuiltPrice": "£4,200 - £5,800",
                "cta": "Get quotes for EGG Dodge Durango engine replacement",
                "image": "/images/brands/land-rover/engines/land-rover-508pn-engine.webp"
              },
              {
                "code": "ESG",
                "title": "6.4L Petrol (392)",
                "familyHeading": "Performance HEMI Family (2018-2024)",
                "history": "The 392 HEMI brought SRT-level performance to the Durango, with forged internals and high-flow heads.",
                "fuel": "Petrol",
                "size": "6.4 Litre",
                "power": "475 hp",
                "years": "2018-2024",
                "compatibleVariants": [
                  "SRT 392, SRT 392 Plus, SRT 392 Premium, AWD only"
                ],
                "commonFailures": [
                  "Valve spring fatigue - high-RPM use can cause spring failure, documented on performance forums",
                  "Piston ring land wear - aggressive driving accelerates wear, monitor compression on high-mileage units",
                  "Oil consumption under load - normal for performance engine but requires vigilant monitoring"
                ],
                "avgRebuiltPrice": "£6,500 - £9,500",
                "cta": "Get quotes for ESG 392 Dodge Durango engine replacement",
                "image": "/images/brands/land-rover/engines/land-rover-508pn-engine.webp"
              },
              {
                "code": "EJH",
                "title": "6.2L Supercharged Petrol (Hellcat)",
                "familyHeading": "Performance HEMI Family (2018-2024)",
                "history": "The supercharged Hellcat V8 made the Durango the most powerful SUV in its class, with specialised calibration.",
                "fuel": "Petrol",
                "size": "6.2 Litre",
                "power": "710 hp",
                "years": "2021-2024",
                "compatibleVariants": [
                  "SRT Hellcat, SRT Hellcat Hammerhead, SRT Hellcat Silver Bullet, SRT Hellcat Brass Monkey"
                ],
                "commonFailures": [
                  "Supercharger coupler wear - high torque loads can cause driveline lash, requires inspection",
                  "Heat exchanger efficiency loss - cooling system critical for sustained performance, monitor temperatures",
                  "Fuel pump demand - high-pressure pump wear under aggressive use, replacement recommended at 50k miles"
                ],
                "avgRebuiltPrice": "£8,500 - £12,500",
                "cta": "Get quotes for EJH Hellcat Dodge Durango engine replacement",
                "image": "/images/brands/land-rover/engines/land-rover-508pn-engine.webp"
              }
            ]
          },
          {
            "name": "Diesel Engines",
            "entries": [
              {
                "code": "EXF",
                "title": "3.0L Diesel",
                "familyHeading": "EcoDiesel V6 Family (2014-2020)",
                "history": "The VM Motori-sourced EcoDiesel offered strong torque and fuel economy for UK Durango buyers, with complex emissions systems.",
                "fuel": "Diesel",
                "size": "3.0 Litre",
                "power": "240-260 hp",
                "years": "2014-2020",
                "compatibleVariants": [
                  "EcoDiesel AWD, EcoDiesel GT, EcoDiesel Citadel, WK2 chassis only"
                ],
                "commonFailures": [
                  "EGR cooler crack - thermal fatigue causes coolant leak into intake, NHTSA recall W79 applies",
                  "Injector carbon buildup - diesel injector coking leads to misfire, requires professional cleaning or replacement",
                  "DPF regeneration issues - blocked filter from short-journey driving causes power loss and warning lights"
                ],
                "avgRebuiltPrice": "£4,800 - £6,500",
                "cta": "Get quotes for EXF EcoDiesel Dodge Durango engine replacement",
                "image": "/images/brands/land-rover/engines/land-rover-aj20d6-engine.webp"
              }
            ]
          }
        ],
        "closing": "Can't find your engine code? Enter your registration number above - we'll instantly identify the exact unit, its technical specifications, and live replacement prices from UK Dodge Durango engine specialists. Every rebuilt engine comes with a minimum 12‑month unlimited mileage warranty."
      },
      "headingLines": [
        "Dodge Durango Engine Replacement",
        "All Variants Covered"
      ],
      "ui": {
        "fromPriceLabel": "from price",
        "specsLabel": "Specs",
        "rebuiltLabel": "Rebuilt",
        "yearsLabel": "Years",
        "yearsFallback": "Check exact year coverage by registration"
      }
    },
    "engineCodes": {
      "tag": "Engine Codes",
      "h2": "Dodge Durango Engine Codes - Full Technical Specifications & Replacement Guide",
      "h3": "Every engine code fitted to the Dodge Durango across all generations, with technical specs, compatible variants and trims, known failure points, and average rebuilt prices from UK specialists. Select any engine code to compare quotes.",
      "closingLine": "Can't find your engine code? Enter your registration number above - we'll instantly identify the exact unit, its technical specifications, and live replacement prices from UK Dodge Durango engine specialists. Every rebuilt engine comes with a minimum 12‑month unlimited mileage warranty.",
      "filters": [
        "Petrol Engines",
        "Diesel Engines"
      ],
      "groups": [
        {
          "name": "Petrol Engines",
          "era": "Extracted from detailed petrol and performance engine families across Dodge Durango variants.",
          "failureNote": "Main replacement demand comes from timing-chain, cooling-system and performance thermal-management faults.",
          "engines": [
            {
              "code": "ERB",
              "title": "3.6L Petrol",
              "familyHeading": "Pentastar V6 Family (2011-2024)",
              "fuel": "Petrol",
              "size": "3.6L",
              "power": "293-295 hp",
              "compatibleModels": "SXT, GT, Citadel, AWD, RWD, WK2, WD",
              "avgRebuiltPrice": "£3,500 - £5,500",
              "cta": "Get quotes for ERB Dodge Durango engine replacement",
              "image": "/images/brands/land-rover/engines/land-rover-508pn-engine.webp"
            },
            {
              "code": "ESG",
              "title": "3.6L Petrol",
              "familyHeading": "Pentastar V6 Family (2011-2024)",
              "fuel": "Petrol",
              "size": "3.6L",
              "power": "293-295 hp",
              "compatibleModels": "SXT WD, GT WD, Citadel WD, AWD WD",
              "avgRebuiltPrice": "£3,500 - £5,500",
              "cta": "Get quotes for ESG Dodge Durango engine replacement",
              "image": "/images/brands/land-rover/engines/land-rover-508pn-engine.webp"
            },
            {
              "code": "ESH",
              "title": "3.6L Petrol",
              "familyHeading": "Pentastar V6 Family (2011-2024)",
              "fuel": "Petrol",
              "size": "3.6L",
              "power": "293-295 hp",
              "compatibleModels": "GT, Citadel, R/T (where 3.6L specified), AWD",
              "avgRebuiltPrice": "£3,500 - £5,500",
              "cta": "Get quotes for ESH Dodge Durango engine replacement",
              "image": "/images/brands/land-rover/engines/land-rover-508pn-engine.webp"
            },
            {
              "code": "EZH",
              "title": "5.7L Petrol",
              "familyHeading": "HEMI V8 Family (2011-2024)",
              "fuel": "Petrol",
              "size": "5.7L",
              "power": "360-395 hp",
              "compatibleModels": "R/T, Citadel, GT Plus, AWD, RWD, WK2, WD",
              "avgRebuiltPrice": "£4,200 - £5,800",
              "cta": "Get quotes for EZH Dodge Durango engine replacement",
              "image": "/images/brands/land-rover/engines/land-rover-508pn-engine.webp"
            },
            {
              "code": "EZH-T",
              "title": "5.7L Petrol",
              "familyHeading": "HEMI V8 Family (2011-2024)",
              "fuel": "Petrol",
              "size": "5.7L",
              "power": "360-395 hp",
              "compatibleModels": "R/T WD, Citadel WD, GT Plus WD, AWD WD",
              "avgRebuiltPrice": "£4,200 - £5,800",
              "cta": "Get quotes for EZH-T Dodge Durango engine replacement",
              "image": "/images/brands/land-rover/engines/land-rover-508pn-engine.webp"
            },
            {
              "code": "EGG",
              "title": "5.7L Petrol",
              "familyHeading": "HEMI V8 Family (2011-2024)",
              "fuel": "Petrol",
              "size": "5.7L",
              "power": "360 hp",
              "compatibleModels": "R/T WK2, Citadel WK2, AWD WK2",
              "avgRebuiltPrice": "£4,200 - £5,800",
              "cta": "Get quotes for EGG Dodge Durango engine replacement",
              "image": "/images/brands/land-rover/engines/land-rover-508pn-engine.webp"
            },
            {
              "code": "ESG",
              "title": "6.4L Petrol (392)",
              "familyHeading": "Performance HEMI Family (2018-2024)",
              "fuel": "Petrol",
              "size": "6.4L",
              "power": "475 hp",
              "compatibleModels": "SRT 392, SRT 392 Plus, SRT 392 Premium, AWD only",
              "avgRebuiltPrice": "£6,500 - £9,500",
              "cta": "Get quotes for ESG 392 Dodge Durango engine replacement",
              "image": "/images/brands/land-rover/engines/land-rover-508pn-engine.webp"
            },
            {
              "code": "EJH",
              "title": "6.2L Supercharged Petrol (Hellcat)",
              "familyHeading": "Performance HEMI Family (2018-2024)",
              "fuel": "Petrol",
              "size": "6.2L",
              "power": "710 hp",
              "compatibleModels": "SRT Hellcat, SRT Hellcat Hammerhead, SRT Hellcat Silver Bullet, SRT Hellcat Brass Monkey",
              "avgRebuiltPrice": "£8,500 - £12,500",
              "cta": "Get quotes for EJH Hellcat Dodge Durango engine replacement",
              "image": "/images/brands/land-rover/engines/land-rover-508pn-engine.webp"
            }
          ]
        },
        {
          "name": "Diesel Engines",
          "era": "Extracted from detailed diesel engine families across Dodge Durango variants.",
          "failureNote": "Main replacement triggers are timing chain wear, EGR / cooling faults and turbo-control issues.",
          "engines": [
            {
              "code": "EXF",
              "title": "3.0L Diesel",
              "familyHeading": "EcoDiesel V6 Family (2014-2020)",
              "fuel": "Diesel",
              "size": "3.0L",
              "power": "240-260 hp",
              "compatibleModels": "EcoDiesel AWD, EcoDiesel GT, EcoDiesel Citadel, WK2 chassis only",
              "avgRebuiltPrice": "£4,800 - £6,500",
              "cta": "Get quotes for EXF EcoDiesel Dodge Durango engine replacement",
              "image": "/images/brands/land-rover/engines/land-rover-aj20d6-engine.webp"
            }
          ]
        }
      ],
      "headingLines": [
        "Dodge Durango Engine Codes",
        "Full Technical Specifications & Replacement Guide"
      ],
      "closingAction": {
        "title": "Can't find your engine code?",
        "buttonText": "Enter Your Reg"
      },
      "ui": {
        "summaryPriceLabel": "Avg. rebuilt price",
        "exampleImageLabel": "Example engine visual",
        "historyLabel": "Engine History",
        "variantsLabel": "Compatible Dodge Durango variants",
        "specsTitle": "Technical Specifications",
        "fuelLabel": "Fuel type",
        "sizeLabel": "Engine size",
        "powerLabel": "Power output",
        "yearsLabel": "Years fitted",
        "failuresTitle": "Common Failures",
        "supplyLabel": "Supply only"
      }
    },
    "commonProblems": {
      "tag": "Common Problems",
      "h2": "Dodge Durango Engine Problems - What It Costs to Fix & When Replacement Makes Sense",
      "h3": "The Dodge Durango's most common replacement engines in the UK are the 3.6L Pentastar V6 and 5.7L HEMI V8, with timing chain, lifter and valve seat issues driving enquiries. Every rebuilt engine supplied through EngineMarket includes upgraded internal components designed to address the original failure point - plus a minimum 12‑month unlimited mileage warranty. Use the cost comparisons below to decide between repair and replacement.",
      "problems": [
        {
          "group": "Pentastar Timing Chain Stretch",
          "h4": "Pentastar Timing Chain Stretch - Why 3.6L Durango Engines Rattle Prematurely",
          "affectedModels": "Dodge Durango SXT, GT, Citadel (2011-2024, ERB/ESG/ESH Pentastar 3.6L)",
          "typicalFailureMileage": "60,000-100,000 miles",
          "rootCause": "Hydraulic tensioner wear allows chain slack, causing rattling noise on cold start and potential jump if ignored.",
          "repairOptions": [
            {
              "tier": "Minor - Preventative Tensioner Replacement - Replace tensioner and guides before chain jump",
              "dealerPrice": "£1,800 - £2,800",
              "specialistPrice": "£1,200 - £1,900",
              "whatItInvolves": "Remove front cover, replace tensioner, guides and chain if stretched",
              "longevity": "Viable only if caught early before chain jump; adds 40-60k miles if successful"
            },
            {
              "tier": "Full Replacement - Rebuilt Pentastar Engine - Supply & fit rebuilt unit with upgraded tensioners",
              "dealerPrice": "£5,200 - £7,500",
              "specialistPrice": "£3,500 - £5,500",
              "whatItInvolves": "Complete engine swap with rebuilt unit featuring upgraded tensioners, bench-tested, 12-month warranty",
              "longevity": "Best value for engines with jump damage or over 90k miles; eliminates repeat risk"
            }
          ],
          "recommendation": "If your Durango shows early chain rattle under 70k miles and compression is good, a preventative tensioner job from a specialist offers better value. If the chain has jumped or mileage exceeds 90k, a rebuilt engine with upgraded components is the safer long-term investment.",
          "cta": "Compare rebuilt Pentastar engine prices for your Dodge Durango"
        },
        {
          "group": "HEMI Lifter Tick",
          "h4": "HEMI Lifter Tick - Why 5.7L Durango Engines Develop Ticking Noise",
          "affectedModels": "Dodge Durango R/T, Citadel, GT Plus (2011-2024, EZH/EZH-T/EGG HEMI 5.7L)",
          "typicalFailureMileage": "70,000-110,000 miles",
          "rootCause": "Hydraulic lifter collapse due to oil aeration or wear, causing metallic ticking and potential camshaft damage if ignored.",
          "repairOptions": [
            {
              "tier": "Intermediate - Lifter & Cam Inspection - Replace collapsed lifters, inspect cam lobes",
              "dealerPrice": "£2,400 - £3,800",
              "specialistPrice": "£1,600 - £2,600",
              "whatItInvolves": "Remove valve covers, replace affected lifters, inspect cam for scoring, MDS solenoid check",
              "longevity": "Only viable if cam lobes are undamaged; risk of repeat if root cause not addressed"
            },
            {
              "tier": "Full Replacement - Rebuilt HEMI Engine - Supply & fit rebuilt unit with upgraded lifters and MDS components",
              "dealerPrice": "£6,000 - £8,500",
              "specialistPrice": "£4,200 - £5,800",
              "whatItInvolves": "Complete engine swap with rebuilt HEMI featuring upgraded lifters, MDS solenoids, bench-tested, 12-month warranty",
              "longevity": "Recommended for engines with cam damage, high mileage, or repeat lifter failures"
            }
          ],
          "recommendation": "On a Durango R/T worth £15k-£25k, if the cam is scored or mileage exceeds 90k, a rebuilt HEMI with upgraded lifters offers better long-term value than repeated lifter repairs. For early-stage tick under 75k miles with good oil history, specialist lifter replacement may suffice.",
          "cta": "Get quotes for rebuilt HEMI engine for your Dodge Durango"
        },
        {
          "group": "HEMI Valve Seat Recession",
          "h4": "HEMI Valve Seat Recession - Why Compression Drops on High-Mileage 5.7L Units",
          "affectedModels": "Dodge Durango R/T, Citadel (2011-2017, EGG/EZH early HEMI 5.7L)",
          "typicalFailureMileage": "90,000-130,000 miles",
          "rootCause": "Intake valve seat dropout due to material fatigue, causing compression loss, misfire and potential piston damage.",
          "repairOptions": [
            {
              "tier": "Major - Cylinder Head Repair - Remove heads, replace valve seats, valve job",
              "dealerPrice": "£3,200 - £4,800",
              "specialistPrice": "£2,200 - £3,400",
              "whatItInvolves": "Remove both cylinder heads, machine seats, replace valves, reassemble with new gaskets",
              "longevity": "Viable only if block and pistons are undamaged; labour-intensive with repeat risk on early codes"
            },
            {
              "tier": "Full Replacement - Rebuilt HEMI Engine - Supply & fit rebuilt unit with upgraded valve seats",
              "dealerPrice": "£6,000 - £8,500",
              "specialistPrice": "£4,200 - £5,800",
              "whatItInvolves": "Complete engine swap with rebuilt HEMI featuring upgraded valve seats, bench-tested, 12-month warranty",
              "longevity": "Best option for engines with piston scoring or over 100k miles; eliminates repeat seat failure risk"
            }
          ],
          "recommendation": "Valve seat recession is a fundamental design limitation on early HEMI codes. If your Durango shows compression loss or misfire on one cylinder, a rebuilt engine with upgraded seats is the only reliable long-term solution - head repair alone rarely prevents recurrence.",
          "cta": "Compare HEMI valve seat upgrade engine prices for your Dodge Durango"
        },
        {
          "group": "EcoDiesel EGR Cooler Failure",
          "h4": "EcoDiesel EGR Cooler Failure - Why 3.0L Durango Diesel Engines Overheat",
          "affectedModels": "Dodge Durango EcoDiesel AWD, GT, Citadel (2014-2020, EXF EcoDiesel 3.0L)",
          "typicalFailureMileage": "80,000-120,000 miles",
          "rootCause": "Thermal fatigue cracks the EGR cooler, allowing coolant vapour into the intake where it can combust, risking catastrophic damage.",
          "repairOptions": [
            {
              "tier": "Minor - EGR Cooler Replacement - Replace cooler with updated part, clean intake",
              "dealerPrice": "£2,600 - £3,900",
              "specialistPrice": "£1,800 - £2,800",
              "whatItInvolves": "Remove intake manifold, replace EGR cooler with revised part, clean carbon from intake runners",
              "longevity": "Viable only if caught before combustion event; NHTSA recall W79 may cover some units"
            },
            {
              "tier": "Full Replacement - Rebuilt EcoDiesel Engine - Supply & fit rebuilt unit with upgraded EGR system",
              "dealerPrice": "£6,800 - £9,200",
              "specialistPrice": "£4,800 - £6,500",
              "whatItInvolves": "Complete engine swap with rebuilt EcoDiesel featuring upgraded EGR components, bench-tested, 12-month warranty",
              "longevity": "Recommended if combustion damage occurred or mileage exceeds 100k; eliminates repeat cooler failure risk"
            }
          ],
          "recommendation": "If your EcoDiesel Durango shows coolant loss without external leak or white smoke, stop driving immediately and have the EGR cooler inspected. If combustion damage is confirmed, only a rebuilt engine with upgraded components offers reliable long-term protection.",
          "cta": "Get quotes for rebuilt EcoDiesel engine for your Dodge Durango"
        },
        {
          "group": "Pentastar Water Pump Failure",
          "h4": "Pentastar Water Pump Failure - Why 3.6L Durango Engines Lose Coolant Internally",
          "affectedModels": "Dodge Durango SXT, GT, Citadel (2011-2024, ERB/ESG/ESH Pentastar 3.6L)",
          "typicalFailureMileage": "70,000-110,000 miles",
          "rootCause": "Internal seal failure in the water pump allows coolant to leak into the oil system or externally without visible puddle.",
          "repairOptions": [
            {
              "tier": "Minor - Water Pump Replacement - Replace pump with updated seal design, flush system",
              "dealerPrice": "£1,400 - £2,200",
              "specialistPrice": "£900 - £1,500",
              "whatItInvolves": "Remove accessory drive, replace water pump with revised part, flush cooling system, refill with correct coolant",
              "longevity": "Viable if caught before oil contamination or overheating; adds 50-70k miles with proper maintenance"
            },
            {
              "tier": "Full Replacement - Rebuilt Pentastar Engine - Supply & fit rebuilt unit with upgraded water pump",
              "dealerPrice": "£5,200 - £7,500",
              "specialistPrice": "£3,500 - £5,500",
              "whatItInvolves": "Complete engine swap with rebuilt Pentastar featuring upgraded water pump, bench-tested, 12-month warranty",
              "longevity": "Recommended if oil contamination occurred, engine overheated, or mileage exceeds 100k"
            }
          ],
          "recommendation": "If your Pentastar Durango shows coolant loss without external leak but no overheating or oil contamination, a specialist water pump replacement with the updated seal design is cost-effective. If the engine overheated or shows milky oil, a rebuilt engine is the safer investment.",
          "cta": "Compare rebuilt Pentastar water pump upgrade prices for your Dodge Durango"
        }
      ],
      "finalCta": {
        "h4": "Don't Let Engine Failure Write Off Your Dodge Durango",
        "paragraph": "Whether your Durango suffers from Pentastar timing chain rattle, HEMI lifter tick, or EcoDiesel EGR failure, EngineMarket makes it simple to compare prices from trusted UK specialists who understand Dodge's proprietary MDS and PCM systems. Every rebuilt engine includes upgraded components addressing the original failure point, bench testing, and a minimum 12‑month unlimited mileage warranty with nationwide delivery. Compare quotes today and get back on the road without the main dealer premium.",
        "buttonText": "Compare Dodge Durango Engine Replacement Prices Now →",
        "disclaimer": "All prices are indicative UK market ranges based on historical quote data and repair requests from our network of engine specialists. Dealer pricing is estimated based on published main dealer labour rates and genuine OEM parts pricing. Specialist pricing reflects actual quote data from EngineMarket's UK network. Actual costs vary depending on damage severity, vehicle condition, variant, and workshop location within the UK. Use our free comparison tool to get tailored quotes for your specific Dodge Durango and engine code. Every engine supplied through EngineMarket carries a minimum 12‑month unlimited mileage warranty - always confirm exact terms with your chosen supplier."
      }
    },
    "engineTypes": {
      "tag": "Replacement Engine Options",
      "h2": "Dodge Durango Engine Types - Options, Costs & What to Expect",
      "intro": "Every Dodge Durango engine type is available through our UK network with typical price ranges based on variant, engine code and budget.",
      "types": [
        {
          "title": "Dodge Durango Reconditioned Engines (Recon)",
          "description": "Professionally restored Durango engines with worn parts replaced, tested to UK standards.",
          "frontDescription": "Professionally restored Durango engines with worn parts replaced, tested to UK standards.",
          "frontDisclaimer": "Suitability depends on engine code and variant.",
          "backDescription": "Reconditioned Durango engines undergo partial disassembly, cleaning and replacement of worn components like bearings and seals.",
          "backBullets": [
            "Ideal for engines with minor wear, no catastrophic damage",
            "Faster turnaround than full rebuild, typically 3-5 days",
            "12-month warranty included when sourced via EngineMarket"
          ],
          "priceRange": "£3,200 - £5,200 (supply only)",
          "cta": "Compare reconditioned Dodge Durango engine prices"
        },
        {
          "title": "Dodge Durango Rebuilt Engines",
          "description": "Comprehensive Durango engine rebuild with upgraded components addressing known failure points.",
          "frontDescription": "Comprehensive Durango engine rebuild with upgraded components addressing known failure points.",
          "frontDisclaimer": "Price varies by engine code and failure severity.",
          "backDescription": "Rebuilt Durango engines are fully disassembled, machined to spec, and fitted with upgraded parts like tensioners or lifters.",
          "backBullets": [
            "Best value for engines with documented failure patterns like timing chain or lifter tick",
            "Upgraded components reduce repeat failure risk versus standard repair",
            "Bench-tested before dispatch, 12-month unlimited mileage warranty"
          ],
          "priceRange": "£3,500 - £5,800 (supply only)",
          "cta": "Get rebuilt Dodge Durango engine quotes"
        },
        {
          "title": "Dodge Durango Used Engines",
          "description": "Low-mileage Durango engines from verified UK breakers, compression-tested before supply.",
          "frontDescription": "Low-mileage Durango engines from verified UK breakers, compression-tested before supply.",
          "frontDisclaimer": "Availability varies; warranty terms differ by supplier.",
          "backDescription": "Used Durango engines offer budget replacement but require careful verification of mileage, compression and service history.",
          "backBullets": [
            "Suitable for low-budget repairs where engine history is documented",
            "Always request compression test results and service records before purchase",
            "EngineMarket suppliers include 3-6 month warranty on verified units"
          ],
          "priceRange": "£2,200 - £4,200 (supply only)",
          "cta": "Check used Dodge Durango engine availability"
        },
        {
          "title": "Dodge Durango Remanufactured Engines",
          "description": "Factory-spec Durango engines rebuilt to original tolerances with all new wear components.",
          "frontDescription": "Factory-spec Durango engines rebuilt to original tolerances with all new wear components.",
          "frontDisclaimer": "Premium option; lead times may apply for low-volume codes.",
          "backDescription": "Remanufactured Durango engines meet or exceed factory specifications with all new bearings, seals, gaskets and critical components.",
          "backBullets": [
            "Best for high-value variants like R/T, Citadel or SRT where longevity is priority",
            "Includes updated parts addressing known TSBs for your engine code",
            "Full bench testing, dyno verification, 12-24 month warranty options"
          ],
          "priceRange": "£4,500 - £7,200 (supply only)",
          "cta": "Compare remanufactured Dodge Durango engine costs"
        },
        {
          "title": "Dodge Durango Refurbished Engines",
          "description": "Mid-tier Durango engine restoration focusing on critical wear items and performance verification.",
          "frontDescription": "Mid-tier Durango engine restoration focusing on critical wear items and performance verification.",
          "frontDisclaimer": "Scope varies by supplier; confirm inclusions before ordering.",
          "backDescription": "Refurbished Durango engines receive targeted renewal of high-wear components like lifters, tensioners and water pumps.",
          "backBullets": [
            "Cost-effective middle ground between used and full rebuild options",
            "Ideal for engines with single-point failures rather than systemic wear",
            "Compression and leak-down tested, 6-12 month warranty typical"
          ],
          "priceRange": "£3,000 - £4,800 (supply only)",
          "cta": "View refurbished Dodge Durango engine options"
        },
        {
          "title": "Dodge Durango Supply & Fit Engines",
          "description": "Complete Durango engine replacement including labour, fluids and post-install calibration at UK specialist garages.",
          "frontDescription": "Complete Durango engine replacement including labour, fluids and post-install calibration at UK specialist garages.",
          "frontDisclaimer": "Labour cost varies by location and garage rate; PCM calibration may incur extra fee.",
          "backDescription": "Supply & fit for Durango engines includes removal of failed unit, installation of replacement, fluid refill and PCM/MDS calibration where required.",
          "backBullets": [
            "Removes DIY complexity for owners without specialist tools or lifting equipment",
            "Ensures MDS solenoids and VVT systems are correctly calibrated post-install",
            "EngineMarket network garages offer warranty on both parts and labour"
          ],
          "priceRange": "£800 - £1,800 added to engine price",
          "cta": "Find Dodge Durango engine supply & fit deals"
        }
      ],
      "closing": "All engine types include a minimum 12‑month unlimited mileage warranty when sourced through EngineMarket. Prices are typical UK market ranges based on historical quote data from our network and depend on exact engine code, variant, mileage and supplier. Use our free comparison tool above - enter your registration to get tailored quotes for your specific Dodge Durango within hours.",
      "headingLines": [
        "Dodge Durango Engine Types",
        "Options, Costs & What to Expect"
      ],
      "ui": {
        "priceLabel": "Typical price range",
        "frontActionLabel": "What is it?",
        "backActionLabel": "Flip back"
      },
      "closingCard": {
        "label": "Engine Replacement Help",
        "title": "Compare Dodge Durango engine prices with vetted UK suppliers",
        "buttonText": "Compare Dodge Durango Prices"
      }
    },
    "engineSizes": {
      "tag": "Engine Sizes",
      "h2": "Dodge Durango Engines by Size - Find the Right Displacement for Your Variant",
      "intro": "Every displacement fitted to the Dodge Durango in the UK is listed below, with compatible engine codes, production years and common failure notes to help you identify the right replacement.",
      "groups": [
        {
          "title": "Dodge Durango Petrol Engine Sizes",
          "items": [
            {
              "title": "Dodge Durango 3.6L Petrol Engines",
              "description": "The 3.6L Pentastar V6 powered most UK Durango variants from 2011, offering a balance of power and efficiency with VVT technology; it remains the most commonly replaced engine due to timing chain and water pump failure patterns.",
              "engineCodes": [
                "ERB",
                "ESG",
                "ESH",
                "ESA",
                "ESB",
                "ESD",
                "ESJ"
              ],
              "compatibleModels": [
                "SXT (2011-2024)",
                "GT (2011-2024)",
                "Citadel (2011-2024)",
                "AWD/RWD variants",
                "WK2 & WD chassis"
              ],
              "productionYears": "",
              "commonFailurePoints": [
                "Timing chain tensioner wear causing rattle; internal water pump seal failure leading to coolant loss"
              ],
              "cta": "Get quotes for Dodge Durango 3.6L petrol engines"
            },
            {
              "title": "Dodge Durango 5.7L Petrol Engines",
              "description": "The 5.7L HEMI V8 brought V8 power to UK Durango R/T and Citadel trims, featuring MDS cylinder deactivation for fuel economy but introducing lifter and valve seat failure risks on higher-mileage units.",
              "engineCodes": [
                "EZH",
                "EZH-T",
                "EGG",
                "ESH HEMI",
                "9EZH"
              ],
              "compatibleModels": [
                "R/T (2011-2024)",
                "Citadel (2011-2024)",
                "GT Plus (2014-2024)",
                "AWD/RWD variants",
                "WK2 & WD chassis"
              ],
              "productionYears": "",
              "commonFailurePoints": [
                "Hydraulic lifter collapse causing metallic tick; intake valve seat recession leading to compression loss"
              ],
              "cta": "Compare Dodge Durango 5.7L petrol engine prices"
            },
            {
              "title": "Dodge Durango 6.4L Petrol Engines",
              "description": "The 6.4L 392 HEMI delivered SRT-level performance to the Durango from 2018, with forged internals and high-flow heads, but requires specialist knowledge for replacement due to performance-specific calibration.",
              "engineCodes": [
                "ESG (392)"
              ],
              "compatibleModels": [
                "SRT 392 (2018-2024)",
                "SRT 392 Plus",
                "SRT 392 Premium",
                "AWD only",
                "WD chassis"
              ],
              "productionYears": "",
              "commonFailurePoints": [
                "Valve spring fatigue under high-RPM use; piston ring land wear with aggressive driving"
              ],
              "cta": "Compare Dodge Durango 6.4L petrol engine prices"
            },
            {
              "title": "Dodge Durango 6.2L Petrol Engines",
              "description": "The supercharged 6.2L Hellcat V8 made the Durango the most powerful SUV in its class from 2021, with specialised PCM calibration and cooling requirements that demand expert handling during replacement.",
              "engineCodes": [
                "EJH"
              ],
              "compatibleModels": [
                "SRT Hellcat (2021-2024)",
                "Hammerhead",
                "Silver Bullet",
                "Brass Monkey editions",
                "AWD only"
              ],
              "productionYears": "",
              "commonFailurePoints": [
                "Supercharger coupler wear under high torque loads; heat exchanger efficiency loss affecting sustained performance"
              ],
              "cta": "Compare Dodge Durango 6.2L petrol engine prices"
            }
          ]
        },
        {
          "title": "Dodge Durango Diesel Engine Sizes",
          "items": [
            {
              "title": "Dodge Durango 3.0L Diesel Engines",
              "description": "The 3.0L EcoDiesel V6 offered strong torque and fuel economy for UK Durango buyers from 2014-2020, but complex emissions systems including the EGR cooler introduced specific failure patterns requiring specialist attention.",
              "engineCodes": [
                "EXF"
              ],
              "compatibleModels": [
                "EcoDiesel AWD (2014-2020)",
                "EcoDiesel GT",
                "EcoDiesel Citadel",
                "WK2 chassis only"
              ],
              "productionYears": "",
              "commonFailurePoints": [
                "EGR cooler thermal fatigue causing coolant leak into intake; injector carbon buildup leading to misfire"
              ],
              "cta": "Get quotes for Dodge Durango 3.0L diesel engines"
            }
          ]
        }
      ],
      "closing": "Not sure which engine size your Dodge Durango needs? Enter your registration number above - we'll identify the exact displacement, engine code and compatible replacement options instantly. All engines supplied through EngineMarket include a minimum 12‑month unlimited mileage warranty from UK Dodge Durango specialists.",
      "headingLines": [
        "Dodge Durango Engines by Size",
        "Find the Right Displacement for Your Variant"
      ],
      "ui": {
        "swapLabel": "Swap panel",
        "engineCodesLabel": "Engine Code(s)",
        "compatibleModelsLabel": "Compatible Models (UK)",
        "productionYearsLabel": "Production Years",
        "warningLabel": "Common Failure Points",
        "warningTitle": "Watch for these known weak points",
        "helperLabel": "Engine Size Advice",
        "helperTitle": "Need help matching the exact engine size?",
        "helperButtonText": "Find My Engine"
      }
    },
    "fuelTypes": {
      "tag": "Fuel Type",
      "h2": "Dodge Durango Engines by Fuel Type",
      "intro": "Choose your Dodge Durango engine by fuel type to compare realistic replacement prices, known issues, and compatible UK supply options - from the economical 3.6L Pentastar to the supercharged 6.2L Hellcat.",
      "items": [
        {
          "title": "Dodge Durango Diesel Engines",
          "description": "The 3.0L EcoDiesel V6 was offered in limited UK Durango variants from 2014-2020, delivering strong torque and fuel economy but requiring specialist knowledge for EGR and DPF system maintenance.",
          "descriptor": "The 3.0L EcoDiesel V6 was offered in limited UK Durango variants from 2014-2020, delivering strong torque and fuel economy but requiring specialist knowledge for EGR and DPF system maintenance.",
          "familiesLabel": "Common Dodge Durango Diesel Engine Families",
          "foundInLabel": "Found In",
          "knownForLabel": "Known For",
          "modelsLabel": "Typical Diesel Models",
          "notesLabel": "",
          "families": [
            "EXF - EcoDiesel 3.0L V6 (EcoDiesel AWD/GT/Citadel), EGR cooler failure risk documented on UK forums"
          ],
          "foundIn": [
            "WK2 chassis EcoDiesel variants (2014-2020) - EXF code only"
          ],
          "knownFor": [
            "Strong low-end torque ideal for towing and motorway cruising",
            "EGR cooler thermal fatigue causing coolant leak into intake - NHTSA recall W79 applies",
            "DPF regeneration issues on short-journey UK driving patterns",
            "Limited UK availability means fewer replacement options versus petrol engines"
          ],
          "typicalModels": [
            "EcoDiesel AWD",
            "EcoDiesel GT",
            "EcoDiesel Citadel"
          ],
          "importantNotes": [],
          "cta": "Get quotes for Dodge Durango Diesel replacement engines"
        },
        {
          "title": "Dodge Durango Petrol Engines",
          "description": "Petrol engines dominate the UK Durango range, with the 3.6L Pentastar V6 and 5.7L HEMI V8 covering most variants, plus high-performance 6.4L and 6.2L options for SRT models.",
          "descriptor": "Petrol engines dominate the UK Durango range, with the 3.6L Pentastar V6 and 5.7L HEMI V8 covering most variants, plus high-performance 6.4L and 6.2L options for SRT models.",
          "familiesLabel": "Common Dodge Durango Petrol Engine Families",
          "foundInLabel": "Found In",
          "knownForLabel": "Known For",
          "modelsLabel": "Typical Petrol Models",
          "notesLabel": "",
          "families": [
            "ERB/ESG/ESH - Pentastar 3.6L V6 (SXT/GT/Citadel), timing chain and water pump failure patterns",
            "EZH/EZH-T/EGG - HEMI 5.7L V8 (R/T/Citadel), lifter tick and valve seat recession risks",
            "ESG (392) - 6.4L HEMI V8 (SRT 392), performance-oriented with specialist rebuild requirements",
            "EJH - 6.2L Supercharged HEMI (SRT Hellcat), ultra-high performance with specialised calibration"
          ],
          "foundIn": [
            "WK2 chassis (2011-2020) - ERB, EZH, EGG, EXF codes",
            "WD chassis facelift (2021-2024) - ESG, EZH-T, ESG 392, EJH codes"
          ],
          "knownFor": [
            "Pentastar 3.6L: Excellent fuel economy for a V6, but timing chain tensioner wear common after 60k miles",
            "HEMI 5.7L: Strong V8 power with MDS fuel-saving tech, but lifter collapse risk on higher-mileage units",
            "392/ Hellcat: Exceptional performance but require specialist knowledge for PCM calibration and cooling system maintenance",
            "All petrol codes: PCM/MDS calibration critical post-replacement to avoid drivability issues"
          ],
          "typicalModels": [
            "SXT",
            "GT",
            "Citadel",
            "R/T",
            "SRT 392",
            "SRT Hellcat"
          ],
          "importantNotes": [],
          "cta": "Compare Dodge Durango Petrol engine prices"
        },
        {
          "title": "Dodge Durango Hybrid / Electrified Engines",
          "description": "The Dodge Durango has not been offered with hybrid or electrified powertrains in the UK market; all variants use conventional petrol or diesel engines.",
          "descriptor": "The Dodge Durango has not been offered with hybrid or electrified powertrains in the UK market; all variants use conventional petrol or diesel engines.",
          "familiesLabel": "Common Dodge Durango Hybrid / Electrified Engine Families",
          "foundInLabel": "",
          "knownForLabel": "",
          "modelsLabel": "",
          "notesLabel": "Important Notes",
          "families": [],
          "foundIn": [],
          "knownFor": [],
          "typicalModels": [],
          "importantNotes": [
            "No MHEV, PHEV, HEV or BEV Durango variants were sold in the UK",
            "All replacement engines are conventional internal combustion units",
            "PCM calibration for MDS/VVT systems remains critical for petrol engine replacements"
          ],
          "cta": "Enquire about Dodge Durango conventional engine availability"
        }
      ],
      "closing": "Not sure which fuel type your Dodge Durango has? Enter your registration number above to instantly identify your engine code, fuel system and compatible replacement options - all backed by a minimum 12‑month unlimited mileage warranty from UK Dodge Durango specialists.",
      "headingLines": [
        "Dodge Durango Engines by Fuel Type"
      ],
      "ui": {
        "swapLabel": "Swap panel",
        "familiesLabel": "Common Engine Families",
        "foundInLabel": "Found In",
        "knownForLabel": "Known For",
        "modelsLabel": "Typical Models (UK)",
        "notesLabel": "Important Notes",
        "closingButtonText": "Find my engine",
        "emptyStateTitle": "Fuel type guidance",
        "emptyStateDescription": "Detailed fuel-type content is being standardised across all brand pages. You can still use the registration form above to identify the correct engine and matching replacement options."
      }
    },
    "engineYears": {
      "tag": "Engine Years",
      "h2": "Dodge Durango Engines by Year - What Was Fitted & When",
      "intro": "This section covers all major engine changes across the Dodge Durango's UK production timeline, organised so owners can quickly identify their engine and compare rebuilt engine prices from UK specialists.",
      "jumpLabel": "Jump to model year",
      "years": [
        {
          "year": "2011 - 2015",
          "preview": "WK2 Launch: Pentastar & HEMI Debut",
          "description": "The third-generation Durango launched in the UK with the new Pentastar 3.6L V6 and optional 5.7L HEMI V8, establishing the engine line-up that would define the model for a decade.",
          "keyChanges": [
            "Introduction of WK2 chassis with unibody construction replacing body-on-frame",
            "Pentastar 3.6L V6 (ERB) becomes standard engine across SXT, GT, Citadel trims",
            "5.7L HEMI V8 (EGG/EZH) optional on R/T and Citadel with MDS cylinder deactivation",
            "8-speed automatic transmission replaces previous 5-speed across all variants"
          ],
          "mainEngines": [
            "ERB - 3.6L petrol (SXT / GT / Citadel)",
            "EGG - 5.7L petrol HEMI (R/T / Citadel)",
            "EZH - 5.7L petrol HEMI with updated MDS calibration (late 2014+)"
          ],
          "popularModels": [
            "Dodge Durango SXT",
            "Dodge Durango GT",
            "Dodge Durango Citadel",
            "Dodge Durango R/T"
          ],
          "knownFor": [
            "Pentastar timing chain tensioner wear emerges as common high-mileage issue",
            "Early HEMI codes (EGG) show higher incidence of lifter tick versus updated EZH",
            "Strong towing capability with HEMI, but fuel economy remains a consideration for UK buyers",
            "Grey import verification critical - many UK units are US-spec with different emissions calibration"
          ],
          "engineCodesCovered": [
            "ERB",
            "EGG",
            "EZH"
          ],
          "cta": "Get quotes for 2011-2015 Dodge Durango replacement engines",
          "badges": [
            {
              "label": "Major Platform Change",
              "tone": "accent"
            }
          ],
          "ticker": "Dodge Durango 2014 Pentastar timing chain replacement • Dodge Durango 2013 HEMI lifter tick fix • Dodge Durango 2015 engine code compatibility check",
          "enquiries": [
            "Dodge Durango 2014 Pentastar timing chain replacement",
            "Dodge Durango 2013 HEMI lifter tick fix",
            "Dodge Durango 2015 engine code compatibility check"
          ]
        },
        {
          "year": "2016 - 2020",
          "preview": "WK2 Matures: Refined Calibration & EcoDiesel Arrival",
          "description": "Mid-cycle updates brought refined PCM calibration for Pentastar and HEMI engines, plus the limited UK introduction of the 3.0L EcoDiesel V6 for improved fuel economy.",
          "keyChanges": [
            "Updated Pentastar codes (ESH) with revised PCM mapping for improved drivability",
            "HEMI MDS calibration refined (EZH-T) to reduce lifter failure incidence",
            "EcoDiesel 3.0L V6 (EXF) introduced for UK market on AWD variants only",
            "Infotainment and safety tech updates, but powertrain architecture unchanged"
          ],
          "mainEngines": [
            "ERB/ESH - 3.6L petrol Pentastar (SXT / GT / Citadel)",
            "EZH/EZH-T - 5.7L petrol HEMI (R/T / Citadel / GT Plus)",
            "EXF - 3.0L diesel EcoDiesel (EcoDiesel AWD / GT / Citadel)"
          ],
          "popularModels": [
            "Dodge Durango GT Plus",
            "Dodge Durango Citadel",
            "Dodge Durango R/T",
            "Dodge Durango EcoDiesel AWD"
          ],
          "knownFor": [
            "Pentastar water pump internal seal failure pattern becomes well-documented on UK forums",
            "HEMI valve seat recession emerges on high-mileage early codes (EGG/EZH pre-2017)",
            "EcoDiesel EGR cooler thermal fatigue leads to NHTSA recall W79 - critical for UK owners to verify compliance",
            "PCM calibration critical post-replacement for MDS/VVT systems to avoid drivability issues"
          ],
          "engineCodesCovered": [
            "ERB",
            "ESH",
            "EZH",
            "EZH-T",
            "EXF"
          ],
          "cta": "Get quotes for 2016-2020 Dodge Durango replacement engines",
          "badges": [
            {
              "label": "Technology Change",
              "tone": "accent"
            }
          ],
          "ticker": "Dodge Durango 2018 Pentastar water pump replacement • Dodge Durango 2017 HEMI valve seat fix • Dodge Durango 2019 EcoDiesel EGR cooler recall",
          "enquiries": [
            "Dodge Durango 2018 Pentastar water pump replacement",
            "Dodge Durango 2017 HEMI valve seat fix",
            "Dodge Durango 2019 EcoDiesel EGR cooler recall"
          ]
        },
        {
          "year": "2021 - 2024",
          "preview": "WD Facelift: Performance Expansion & Updated Codes",
          "description": "The facelifted WD chassis brought updated engine codes across the range, plus the arrival of the high-performance 6.4L 392 and 6.2L Hellcat HEMI for UK SRT variants.",
          "keyChanges": [
            "Updated Pentastar code ESG with refined emissions calibration for WD chassis",
            "HEMI EZH-T becomes standard code for 5.7L applications with improved MDS reliability",
            "SRT 392 (6.4L ESG) and SRT Hellcat (6.2L EJH) introduced for UK market",
            "Enhanced PCM software requiring specialist calibration tools for post-replacement setup"
          ],
          "mainEngines": [
            "ESG - 3.6L petrol Pentastar (SXT / GT / Citadel WD)",
            "EZH-T - 5.7L petrol HEMI (R/T / Citadel / GT Plus WD)",
            "ESG (392) - 6.4L petrol HEMI (SRT 392 WD)",
            "EJH - 6.2L supercharged petrol HEMI (SRT Hellcat WD)"
          ],
          "popularModels": [
            "Dodge Durango SXT WD",
            "Dodge Durango GT Plus WD",
            "Dodge Durango Citadel WD",
            "Dodge Durango SRT 392",
            "Dodge Durango SRT Hellcat"
          ],
          "knownFor": [
            "Updated Pentastar ESG shows improved tensioner durability versus early ERB codes",
            "HEMI EZH-T reduces but does not eliminate lifter tick risk versus early EGG/EZH",
            "SRT 392 and Hellcat require specialist knowledge for PCM calibration and cooling system maintenance",
            "Grey import verification remains critical - many UK WD chassis units are US-spec with different emissions calibration"
          ],
          "engineCodesCovered": [
            "ESG",
            "EZH-T",
            "ESG (392)",
            "EJH"
          ],
          "cta": "Get quotes for 2021-2024 Dodge Durango replacement engines",
          "badges": [
            {
              "label": "Performance Change",
              "tone": "accent"
            }
          ],
          "ticker": "Dodge Durango 2022 Pentastar ESG replacement • Dodge Durango 2023 HEMI EZH-T calibration • Dodge Durango 2024 SRT Hellcat engine availability",
          "enquiries": [
            "Dodge Durango 2022 Pentastar ESG replacement",
            "Dodge Durango 2023 HEMI EZH-T calibration",
            "Dodge Durango 2024 SRT Hellcat engine availability"
          ]
        },
        {
          "year": "Pre-2011 - WK1 Legacy: PowerTech Era",
          "preview": "",
          "description": "First-generation Durango models were not officially imported to the UK; any pre-2011 units are grey imports requiring specialist verification for engine compatibility and emissions compliance.",
          "keyChanges": [
            "WK1 chassis used body-on-frame construction with different engine mounting points versus WK2/WD",
            "PowerTech 4.7L V8 and 5.9L V8 were common in US market but rare in UK",
            "No official UK emissions certification for pre-2011 Durango variants"
          ],
          "mainEngines": [
            "PowerTech 4.7L V8 (rare UK grey imports)",
            "5.9L Magnum V8 (very rare UK grey imports)"
          ],
          "popularModels": [
            "Dodge Durango SLT (grey import)",
            "Dodge Durango Limited (grey import)"
          ],
          "knownFor": [
            "Pre-2011 Durango engines require specialist verification for UK MoT emissions compliance",
            "Parts availability limited versus WK2/WD chassis engines",
            "PCM calibration differences between US-spec and UK requirements can cause drivability issues post-replacement"
          ],
          "engineCodesCovered": [
            "PowerTech 4.7L",
            "5.9L Magnum"
          ],
          "cta": "Enquire about pre-2011 Dodge Durango grey import engine compatibility",
          "badges": [
            {
              "label": "Major Platform Change",
              "tone": "accent"
            }
          ],
          "enquiries": []
        }
      ],
      "closing": "Not sure which year your Dodge Durango was built? Enter your registration number and we'll identify the exact engine, model year, and compatible replacement options instantly - all backed by a minimum 12‑month warranty from UK Dodge Durango specialists.",
      "headingLines": [
        "Dodge Durango Engines by Year",
        "What Was Fitted & When"
      ],
      "ui": {
        "keyChangesLabel": "Key Changes",
        "knownForLabel": "Known For",
        "mainEnginesLabel": "Main Engines",
        "popularModelsLabel": "Popular Models",
        "engineCodesLabel": "Engine Codes Covered",
        "enquiriesLabel": "Common Replacement Enquiries"
      },
      "summaryCta": {
        "label": "Year Finder",
        "title": "Not sure which year your Dodge Durango was built?",
        "buttonText": "Find My Engine"
      }
    },
    "faq": {
      "tag": "FAQ",
      "h2": "Dodge Durango Engine Replacement - Frequently Asked Questions",
      "intro": "",
      "items": [
        {
          "question": "How much does a Dodge Durango engine replacement cost in the UK?",
          "answer": "Typical rebuilt engine costs for the Dodge Durango range from £3,500 for the common 3.6L Pentastar to £5,800 for the 5.7L HEMI, with supply-only pricing; supply & fit adds £800-£1,800 depending on garage location.",
          "keyPoints": [
            "3.6L Pentastar rebuilt: £3,500-£5,500 supply only",
            "5.7L HEMI rebuilt: £4,200-£5,800 supply only",
            "EcoDiesel 3.0L rebuilt: £4,800-£6,500 supply only",
            "Supply & fit labour typically adds £800-£1,800 to engine price"
          ],
          "cta": "Compare Dodge Durango engine replacement prices UK"
        },
        {
          "question": "What engine codes fit my Dodge Durango?",
          "answer": "Your Dodge Durango's engine code is identified by the 8th digit of the VIN: ERB/ESG/ESH for 3.6L Pentastar, EZH/EZH-T/EGG for 5.7L HEMI, EXF for 3.0L EcoDiesel, ESG (392) for 6.4L, and EJH for 6.2L Hellcat.",
          "keyPoints": [
            "Check VIN 8th digit for exact engine code match",
            "Pentastar codes: ERB, ESG, ESH, ESA, ESB, ESD, ESJ",
            "HEMI codes: EZH, EZH-T, EGG, ESH HEMI, 9EZH",
            "Use EngineMarket's VIN decoder to verify compatibility instantly"
          ],
          "cta": "Verify your Dodge Durango engine code compatibility now"
        },
        {
          "question": "How long does a Dodge Durango engine replacement take?",
          "answer": "A supply-only Dodge Durango engine typically ships within 3-5 working days from UK stock; supply & fit installations take 2-4 days at specialist garages, depending on parts availability and PCM calibration requirements.",
          "keyPoints": [
            "Supply-only engines: 3-5 working days from UK stock",
            "Supply & fit installations: 2-4 days at specialist garages",
            "PCM/MDS calibration adds 0.5-1 day post-install",
            "Complex variants like SRT Hellcat may require longer lead times"
          ],
          "cta": "Check Dodge Durango engine availability and turnaround times"
        },
        {
          "question": "Do you offer warranty on Dodge Durango replacement engines?",
          "answer": "Yes, every rebuilt or reconditioned Dodge Durango engine supplied through EngineMarket includes a minimum 12‑month unlimited mileage warranty covering parts and labour for manufacturing defects.",
          "keyPoints": [
            "Minimum 12-month unlimited mileage warranty standard",
            "Coverage includes MDS solenoids, VVT actuators, and upgraded failure-point components",
            "Warranty valid at any UK garage; keep service records for claims",
            "Confirm exact terms with your chosen supplier before ordering"
          ],
          "cta": "Get quotes for Dodge Durango engines with 12-month warranty"
        },
        {
          "question": "Can I use a used engine in my Dodge Durango?",
          "answer": "Yes, used Dodge Durango engines are available from £2,200 supply only, but require careful verification of mileage, compression test results, and service history to avoid repeat failure.",
          "keyPoints": [
            "Used engines cost £2,200-£4,200 supply only versus £3,500+ for rebuilt",
            "Always request compression test results and service records before purchase",
            "Used engines typically carry 3-6 month warranty versus 12 months for rebuilt",
            "Best suited for low-budget repairs where engine history is fully documented"
          ],
          "cta": "Compare used versus rebuilt Dodge Durango engine options"
        },
        {
          "question": "Will a replacement engine affect my Dodge Durango MoT?",
          "answer": "A compliant replacement engine will not affect your Dodge Durango's MoT, but emissions-legal engines with correct catalytic converters and O2 sensors are essential for UK MoT pass, especially on grey imports.",
          "keyPoints": [
            "Replacement engines must include MoT-compliant catalytic converters and O2 sensors",
            "Grey import Durangos require emissions verification for UK MoT compliance",
            "EcoDiesel variants must have functional DPF and EGR systems to pass emissions test",
            "EngineMarket suppliers ensure all engines meet UK emissions standards"
          ],
          "cta": "Enquire about MoT-compliant Dodge Durango replacement engines"
        },
        {
          "question": "Do I need ECU reprogramming after Durango engine replacement?",
          "answer": "Yes, Dodge Durango engines with MDS or VVT systems require PCM calibration after replacement to ensure proper cylinder deactivation, variable timing, and drivability; specialist tools are needed for this process.",
          "keyPoints": [
            "MDS solenoids require calibration to avoid rough idle or warning lights",
            "VVT actuators need PCM reset for correct timing advance/retard",
            "SRT variants with performance calibration require specialised software",
            "EngineMarket network garages include PCM calibration in supply & fit packages"
          ],
          "cta": "Find Dodge Durango specialists offering PCM calibration service"
        },
        {
          "question": "How do I know if my Durango needs a rebuilt or used engine?",
          "answer": "Choose a rebuilt Dodge Durango engine if your failure involves timing chain jump, lifter collapse, or valve seat recession; a used engine may suffice for low-mileage units with minor wear and documented service history.",
          "keyPoints": [
            "Rebuilt engines recommended for catastrophic failures or engines over 90k miles",
            "Used engines suitable for low-mileage units with minor wear and full history",
            "Rebuilt engines include upgraded components addressing known failure points",
            "Consider vehicle value: rebuilt engines offer better long-term value for higher-spec variants"
          ],
          "cta": "Get expert advice on rebuilt vs used Dodge Durango engines"
        },
        {
          "question": "Can you supply and fit a Dodge Durango engine near me?",
          "answer": "Yes, EngineMarket's network includes over 100 vetted UK specialists offering supply & fit Dodge Durango engine replacement with nationwide coverage, PCM calibration capability, and warranty on parts and labour.",
          "keyPoints": [
            "Over 100 vetted UK garages in EngineMarket network",
            "Nationwide coverage including London, Manchester, Birmingham, Glasgow",
            "Supply & fit packages include engine, labour, fluids, and PCM calibration",
            "All work backed by minimum 12-month unlimited mileage warranty"
          ],
          "cta": "Find Dodge Durango engine supply & fit specialists near you"
        },
        {
          "question": "What problems do Dodge Durango engines commonly have?",
          "answer": "The most common Dodge Durango engine problems in the UK are Pentastar timing chain stretch (60k-100k miles), HEMI lifter tick (70k-110k miles), and EcoDiesel EGR cooler failure (80k-120k miles).",
          "keyPoints": [
            "Pentastar 3.6L: Timing chain tensioner wear, water pump internal leak",
            "HEMI 5.7L: Hydraulic lifter collapse, valve seat recession, MDS solenoid failure",
            "EcoDiesel 3.0L: EGR cooler thermal fatigue, injector carbon buildup, DPF issues",
            "Early intervention on warning signs can prevent catastrophic engine damage"
          ],
          "cta": "Compare Dodge Durango engine problem repair costs UK"
        }
      ],
      "headingLines": [
        "Dodge Durango Engine Replacement",
        "Frequently Asked Questions"
      ],
      "defaultOpenIndex": 0,
      "ui": {
        "questionLabelPrefix": "Question",
        "keyPointsLabel": "Key points",
        "warningTitle": "Check fitment and engine condition before ordering"
      }
    },
    "trustCta": {
      "tag": "Why Choose Us",
      "h2": "Why UK Dodge Durango Owners Trust EngineMarket",
      "intro": "Join thousands of UK drivers who compare Dodge Durango engine prices through our network of trusted specialists - every rebuilt and reconditioned unit backed by a minimum 12‑month unlimited mileage warranty and nationwide delivery.",
      "points": [
        {
          "title": "Trusted Dodge Durango Engine Suppliers",
          "description": "Every garage and engine rebuilder in our network is vetted, rated, and reviewed by real Dodge Durango owners."
        },
        {
          "title": "Compare Dodge Durango Engine Replacement Companies",
          "description": "See prices, warranty terms, and supply & fit options side‑by‑side before you commit."
        },
        {
          "title": "UK Engine Replacement Services for Dodge Durango",
          "description": "Covering every variant from SXT to SRT Hellcat, with supply‑only or full supply & fit available nationwide."
        }
      ],
      "finalText": "Find the best Dodge Durango engine replacement UK drivers rely on. Compare prices from trusted specialists today and get back on the road with confidence.",
      "buttonText": "Compare Dodge Durango Engine Prices Now →",
      "secondaryAction": {
        "text": "Call Our Experts",
        "href": "tel:03330000044"
      },
      "imageAlt": "Dodge Durango vehicle",
      "ui": {
        "pointLabel": "Included",
        "stripLabel": "Trusted UK Engine Marketplace",
        "stripTitle": "Compare Dodge Durango engine prices with vetted UK specialists",
        "trustBullets": [
          "100% Free",
          "No Obligation",
          "Fast & secure process",
          "UK-based support"
        ],
        "imageBadgeLabel": "Trusted supplier network",
        "imageBadgeTitle": "Warranty-backed rebuilt & used options",
        "imageBadgeText": "Every quote checked for fitment, quality and lead time."
      }
    }
  }
}
